pyDewesoft/DWDataReaderHeader.py
pyDewesoft/DataReader.py
pyDewesoft/__init__.py
pyDewesoft/resources/DWDataReaderLib.dll
pyDewesoft/resources/DWDataReaderLib64.dll
pyDewesoft/resources/EULA-DWDataReader.pdf
pyDewesoft-1.1a0.dist-info/METADATA
pyDewesoft-1.1a0.dist-info/WHEEL
pyDewesoft-1.1a0.dist-info/top_level.txt
pyDewesoft-1.1a0.dist-info/RECORD
