Metadata-Version: 2.1
Name: pyDewesoft
Version: 1.1a0
Summary: A Python module to read Dewesoft datafiles
Home-page: https://github.com/jellespijker/pyDewesoft
Author: Jelle Spijker
Author-email: spijker.jelle@gmail.com
License: MIT License
Keywords: Measurement,Engineering,DSP,Signal processing
Platform: UNKNOWN
Requires-Dist: pint
Requires-Dist: numpy
Requires-Dist: dill
